{
  "לא נמצא שם": {
    "שם": "לא נמצא שם",
    "תפקיד": null,
    "מחלקה": null,
    "רשות": "בית שמש",
    "מייל": null,
    "טלפון פרטי": "050728896",
    "טלפון משרד": null
  },
  "לא נמצא שם (עובדיה)": {
    "שם": "לא נמצא שם (עובדיה)",
    "תפקיד": "עובדיה",
    "מחלקה": null,
    "רשות": "בית שמש",
    "מייל": null,
    "טלפון פרטי": "052764797",
    "טלפון משרד": null
  },
  "לא נמצא שם (מרכז)": {
    "שם": "לא נמצא שם (מרכז)",
    "תפקיד": "מרכז",
    "מחלקה": null,
    "רשות": "בית שמש",
    "מייל": null,
    "טלפון פרטי": "054924645",
    "טלפון משרד": null
  },
  "rouy.mo": {
    "שם": "rouy.mo",
    "תפקיד": null,
    "מחלקה": null,
    "רשות": "בית שמש",
    "מייל": "rouy.mo@gmail.com",
    "טלפון פרטי": null,
    "טלפון משרד": "029917714"
  },
  "ab-han": {
    "שם": "ab-han",
    "תפקיד": null,
    "מחלקה": null,
    "רשות": "בית שמש",
    "מייל": "ab-han@bshemesh.co.il",
    "טלפון פרטי": null,
    "טלפון משרד": "029900768"
  },
  "doritu": {
    "שם": "doritu",
    "תפקיד": null,
    "מחלקה": null,
    "רשות": "בית שמש",
    "מייל": "doritu@bshemesh.co.il",
    "טלפון פרטי": null,
    "טלפון משרד": null
  },
  "shindy": {
    "שם": "shindy",
    "תפקיד": null,
    "מחלקה": null,
    "רשות": "בית שמש",
    "מייל": "shindy@bshemesh.co.il",
    "טלפון פרטי": null,
    "טלפון משרד": "073323632"
  },
  "tehila": {
    "שם": "tehila",
    "תפקיד": null,
    "מחלקה": null,
    "רשות": "בית שמש",
    "מייל": "tehila@bshemesh.co.il",
    "טלפון פרטי": null,
    "טלפון משרד": null
  },
  "Shimon": {
    "שם": "Shimon",
    "תפקיד": "יו\"ר",
    "מחלקה": null,
    "רשות": "בית שמש",
    "מייל": "Shimon@Bshemesh.co.il",
    "טלפון פרטי": null,
    "טלפון משרד": "073323632"
  },
  "guy": {
    "שם": "guy",
    "תפקיד": null,
    "מחלקה": null,
    "רשות": "בית שמש",
    "מייל": "guy@bshemesh.co.il",
    "טלפון פרטי": null,
    "טלפון משרד": "029900763"
  },
  "לא נמצא שם (מנהל)": {
    "שם": "לא נמצא שם (מנהל)",
    "תפקיד": "מנהל",
    "מחלקה": null,
    "רשות": "בית שמש",
    "מייל": "dano@bshemesh.co.il",
    "טלפון פרטי": null,
    "טלפון משרד": null
  },
  "taba": {
    "שם": "taba",
    "תפקיד": "יועצת",
    "מחלקה": null,
    "רשות": "בית שמש",
    "מייל": "taba@bshemesh.co.il",
    "טלפון פרטי": null,
    "טלפון משרד": "073350241"
  },
  "TB-Han": {
    "שם": "TB-Han",
    "תפקיד": "מנהלת",
    "מחלקה": null,
    "רשות": "בית שמש",
    "מייל": "TB-Han@Bshemesh.co.il",
    "טלפון פרטי": null,
    "טלפון משרד": "029900783"
  },
  "mm-han": {
    "שם": "mm-han",
    "תפקיד": "מנהלת",
    "מחלקה": null,
    "רשות": "בית שמש",
    "מייל": "mm-han@Bshemesh.co.il",
    "טלפון פרטי": null,
    "טלפון משרד": null
  },
  "malkaf": {
    "שם": "malkaf",
    "תפקיד": null,
    "מחלקה": null,
    "רשות": "בית שמש",
    "מייל": "malkaf@bshemesh.co.il",
    "טלפון פרטי": null,
    "טלפון משרד": "073394020"
  },
  "MichalK": {
    "שם": "MichalK",
    "תפקיד": null,
    "מחלקה": null,
    "רשות": "בית שמש",
    "מייל": "MichalK@Bshemesh.co.il",
    "טלפון פרטי": null,
    "טלפון משרד": "073394020"
  },
  "elishevag": {
    "שם": "elishevag",
    "תפקיד": null,
    "מחלקה": null,
    "רשות": "בית שמש",
    "מייל": "elishevag@Bshemesh.co.il",
    "טלפון פרטי": null,
    "טלפון משרד": null
  },
  "navc-han": {
    "שם": "navc-han",
    "תפקיד": null,
    "מחלקה": null,
    "רשות": "בית שמש",
    "מייל": "navc-han@Bshemesh.co.il",
    "טלפון פרטי": null,
    "טלפון משרד": null
  },
  "HS-Han": {
    "שם": "HS-Han",
    "תפקיד": null,
    "מחלקה": null,
    "רשות": "בית שמש",
    "מייל": "HS-Han@Bshemesh.co.il",
    "טלפון פרטי": null,
    "טלפון משרד": null
  },
  "SE-Han": {
    "שם": "SE-Han",
    "תפקיד": null,
    "מחלקה": null,
    "רשות": "בית שמש",
    "מייל": "SE-Han@Bshemesh.co.il",
    "טלפון פרטי": null,
    "טלפון משרד": "073323753"
  },
  "RSH-Han": {
    "שם": "RSH-Han",
    "תפקיד": null,
    "מחלקה": null,
    "רשות": "בית שמש",
    "מייל": "RSH-Han@Bshemesh.co.il",
    "טלפון פרטי": null,
    "טלפון משרד": "025954872"
  },
  "yaelp": {
    "שם": "yaelp",
    "תפקיד": null,
    "מחלקה": null,
    "רשות": "בית שמש",
    "מייל": "yaelp@Bshemesh.co.il",
    "טלפון פרטי": null,
    "טלפון משרד": "029900770"
  },
  "hodaya": {
    "שם": "hodaya",
    "תפקיד": null,
    "מחלקה": null,
    "רשות": "בית שמש",
    "מייל": "hodaya@Bshemesh.co.il",
    "טלפון פרטי": null,
    "טלפון משרד": null
  },
  "Rachelb": {
    "שם": "Rachelb",
    "תפקיד": null,
    "מחלקה": null,
    "רשות": "בית שמש",
    "מייל": "Rachelb@Bshemesh.co.il",
    "טלפון פרטי": null,
    "טלפון משרד": null
  },
  "LZ-Han": {
    "שם": "LZ-Han",
    "תפקיד": null,
    "מחלקה": null,
    "רשות": "בית שמש",
    "מייל": "LZ-Han@Bshemesh.co.il",
    "טלפון פרטי": null,
    "טלפון משרד": null
  },
  "ra-han": {
    "שם": "ra-han",
    "תפקיד": null,
    "מחלקה": null,
    "רשות": "בית שמש",
    "מייל": "ra-han@bshemesh.co.il",
    "טלפון פרטי": null,
    "טלפון משרד": "029900784"
  },
  "hodayad": {
    "שם": "hodayad",
    "תפקיד": null,
    "מחלקה": null,
    "רשות": "בית שמש",
    "מייל": "hodayad@bshemesh.co.il",
    "טלפון פרטי": null,
    "טלפון משרד": "074738719"
  },
  "myriamm": {
    "שם": "myriamm",
    "תפקיד": null,
    "מחלקה": null,
    "רשות": "בית שמש",
    "מייל": "myriamm@bshemesh.co.il",
    "טלפון פרטי": null,
    "טלפון משרד": null
  },
  "leahw": {
    "שם": "leahw",
    "תפקיד": null,
    "מחלקה": null,
    "רשות": "בית שמש",
    "מייל": "leahw@bshemesh.co.il",
    "טלפון פרטי": null,
    "טלפון משרד": null
  },
  "NA-Han": {
    "שם": "NA-Han",
    "תפקיד": null,
    "מחלקה": null,
    "רשות": "בית שמש",
    "מייל": "NA-Han@Bshemesh.co.il",
    "טלפון פרטי": null,
    "טלפון משרד": "025944047"
  },
  "ER-Han": {
    "שם": "ER-Han",
    "תפקיד": null,
    "מחלקה": null,
    "רשות": "בית שמש",
    "מייל": "ER-Han@Bshemesh.co.il",
    "טלפון פרטי": null,
    "טלפון משרד": null
  },
  "DB-Han": {
    "שם": "DB-Han",
    "תפקיד": null,
    "מחלקה": null,
    "רשות": "בית שמש",
    "מייל": "DB-Han@Bshemesh.co.il",
    "טלפון פרטי": null,
    "טלפון משרד": null
  },
  "אייל בבני\tפיקוח על הבניה": {
    "שם": "אייל בבני\tפיקוח על הבניה",
    "תפקיד": null,
    "מחלקה": null,
    "רשות": "בית שמש",
    "מייל": "eyalb@Bshemesh.co.il",
    "טלפון פרטי": null,
    "טלפון משרד": null
  },
  "dd-han": {
    "שם": "dd-han",
    "תפקיד": null,
    "מחלקה": null,
    "רשות": "בית שמש",
    "מייל": "dd-han@bshemesh.co.il",
    "טלפון פרטי": null,
    "טלפון משרד": null
  },
  "YL-Han": {
    "שם": "YL-Han",
    "תפקיד": null,
    "מחלקה": null,
    "רשות": "בית שמש",
    "מייל": "YL-Han@Bshemesh.co.il",
    "טלפון פרטי": null,
    "טלפון משרד": "029900763"
  },
  "shaib": {
    "שם": "shaib",
    "תפקיד": null,
    "מחלקה": null,
    "רשות": "בית שמש",
    "מייל": "shaib@bshemesh.co.il",
    "טלפון פרטי": null,
    "טלפון משרד": null
  },
  "avrahams": {
    "שם": "avrahams",
    "תפקיד": null,
    "מחלקה": null,
    "רשות": "בית שמש",
    "מייל": "avrahams@bshemesh.co.il",
    "טלפון פרטי": null,
    "טלפון משרד": null
  },
  "mahmuda": {
    "שם": "mahmuda",
    "תפקיד": null,
    "מחלקה": null,
    "רשות": "בית שמש",
    "מייל": "mahmuda@bshemesh.co.il",
    "טלפון פרטי": null,
    "טלפון משרד": "029900775"
  },
  "AC-Han": {
    "שם": "AC-Han",
    "תפקיד": "מפקח",
    "מחלקה": null,
    "רשות": "בית שמש",
    "מייל": "AC-Han@Bshemesh.co.il",
    "טלפון פרטי": null,
    "טלפון משרד": "025475347"
  },
  "shl-han": {
    "שם": "shl-han",
    "תפקיד": "מפקח",
    "מחלקה": null,
    "רשות": "בית שמש",
    "מייל": "shl-han@bshemesh.co.il",
    "טלפון פרטי": null,
    "טלפון משרד": "023730840"
  },
  "razielo": {
    "שם": "razielo",
    "תפקיד": "מפקח",
    "מחלקה": null,
    "רשות": "בית שמש",
    "מייל": "razielo@bshemesh.co.il",
    "טלפון פרטי": null,
    "טלפון משרד": null
  },
  "shayah": {
    "שם": "shayah",
    "תפקיד": "מפקח",
    "מחלקה": null,
    "רשות": "בית שמש",
    "מייל": "shayah@bshemesh.co.il",
    "טלפון פרטי": null,
    "טלפון משרד": null
  },
  "HM-Han": {
    "שם": "HM-Han",
    "תפקיד": "מנהלת",
    "מחלקה": null,
    "רשות": "בית שמש",
    "מייל": "HM-Han@Bshemesh.co.il",
    "טלפון פרטי": null,
    "טלפון משרד": null
  },
  "MalkaP": {
    "שם": "MalkaP",
    "תפקיד": "רכזת",
    "מחלקה": null,
    "רשות": "בית שמש",
    "מייל": "MalkaP@Bshemesh.co.il",
    "טלפון פרטי": null,
    "טלפון משרד": null
  },
  "gitteld": {
    "שם": "gitteld",
    "תפקיד": null,
    "מחלקה": null,
    "רשות": "בית שמש",
    "מייל": "gitteld@bshemesh.co.il",
    "טלפון פרטי": null,
    "טלפון משרד": null
  },
  "BSJ-HAN": {
    "שם": "BSJ-HAN",
    "תפקיד": null,
    "מחלקה": "מחלקת חינוך",
    "רשות": "בית שמש",
    "מייל": "BSJ-HAN@Bshemesh.co.il",
    "טלפון פרטי": null,
    "טלפון משרד": null
  },
  "asb-han": {
    "שם": "asb-han",
    "תפקיד": null,
    "מחלקה": "מחלקת חינוך",
    "רשות": "בית שמש",
    "מייל": "asb-han@Bshemesh.co.il",
    "טלפון פרטי": null,
    "טלפון משרד": null
  },
  "שרה לדרר\t מבני ציבור חינוך ושצ\"פ": {
    "שם": "שרה לדרר\t מבני ציבור חינוך ושצ\"פ",
    "תפקיד": null,
    "מחלקה": "מחלקת חינוך",
    "רשות": "בית שמש",
    "מייל": "SL-Han@Bshemesh.co.il",
    "טלפון פרטי": null,
    "טלפון משרד": "026418856"
  },
  "cl-han": {
    "שם": "cl-han",
    "תפקיד": null,
    "מחלקה": null,
    "רשות": "בית שמש",
    "מייל": "cl-han@Bshemesh.co.il",
    "טלפון פרטי": null,
    "טלפון משרד": "029900774"
  },
  "rs-han": {
    "שם": "rs-han",
    "תפקיד": null,
    "מחלקה": null,
    "רשות": "בית שמש",
    "מייל": "rs-han@bshemesh.co.il",
    "טלפון פרטי": null,
    "טלפון משרד": "025475352"
  },
  "yk-han": {
    "שם": "yk-han",
    "תפקיד": null,
    "מחלקה": null,
    "רשות": "בית שמש",
    "מייל": "yk-han@bshemesh.co.il",
    "טלפון פרטי": null,
    "טלפון משרד": null
  },
  "nachumj": {
    "שם": "nachumj",
    "תפקיד": null,
    "מחלקה": null,
    "רשות": "בית שמש",
    "מייל": "nachumj@bshemesh.co.il",
    "טלפון פרטי": null,
    "טלפון משרד": null
  },
  "bennyl": {
    "שם": "bennyl",
    "תפקיד": "אחראי",
    "מחלקה": null,
    "רשות": "בית שמש",
    "מייל": "bennyl@bshemesh.co.il",
    "טלפון פרטי": null,
    "טלפון משרד": null
  },
  "brachaha": {
    "שם": "brachaha",
    "תפקיד": null,
    "מחלקה": null,
    "רשות": "בית שמש",
    "מייל": "brachaha@bshemesh.co.il",
    "טלפון פרטי": null,
    "טלפון משרד": null
  },
  "dudis": {
    "שם": "dudis",
    "תפקיד": "מנהל",
    "מחלקה": null,
    "רשות": "בית שמש",
    "מייל": "dudis@bshemesh.co.il",
    "טלפון פרטי": null,
    "טלפון משרד": null
  }
}