{
  "sameer.ab.zed": {
    "שם": "sameer.ab.zed",
    "תפקיד": null,
    "מחלקה": null,
    "רשות": "עיילבון",
    "מייל": "sameer.ab.zed@gmail.com",
    "טלפון פרטי": null,
    "טלפון משרד": null
  },
  "akram.sr": {
    "שם": "akram.sr",
    "תפקיד": null,
    "מחלקה": null,
    "רשות": "עיילבון",
    "מייל": "akram.sr@eilaboun.muni.il",
    "טלפון פרטי": null,
    "טלפון משרד": null
  },
  "basel.zr": {
    "שם": "basel.zr",
    "תפקיד": null,
    "מחלקה": null,
    "רשות": "עיילבון",
    "מייל": "basel.zr@eilaboun.muni.il",
    "טלפון פרטי": null,
    "טלפון משרד": "046782123"
  },
  "גמיל חאיק\tמבקר פנימי למועצה": {
    "שם": "גמיל חאיק\tמבקר פנימי למועצה",
    "תפקיד": null,
    "מחלקה": null,
    "רשות": "עיילבון",
    "מייל": "jamil99@walla.com",
    "טלפון פרטי": null,
    "טלפון משרד": "046782123"
  },
  "לא נמצא שם": {
    "שם": "לא נמצא שם",
    "תפקיד": null,
    "מחלקה": null,
    "רשות": "עיילבון",
    "מייל": "juman310@gmail.com",
    "טלפון פרטי": null,
    "טלפון משרד": null
  },
  "מזכירה ראשית ב\"ס יסודי": {
    "שם": "מזכירה ראשית ב\"ס יסודי",
    "תפקיד": "ראשית",
    "מחלקה": null,
    "רשות": "עיילבון",
    "מייל": "inaamhu@gmail.com",
    "טלפון פרטי": null,
    "טלפון משרד": "046786356"
  },
  "gamila_ha": {
    "שם": "gamila_ha",
    "תפקיד": null,
    "מחלקה": null,
    "רשות": "עיילבון",
    "מייל": "gamila_ha@hotmail.com",
    "טלפון פרטי": null,
    "טלפון משרד": "046786407"
  },
  "עובדת סוציאלית": {
    "שם": "עובדת סוציאלית",
    "תפקיד": "עובדת",
    "מחלקה": null,
    "רשות": "עיילבון",
    "מייל": "halahzr@gmail.com",
    "טלפון פרטי": null,
    "טלפון משרד": "046785810"
  },
  "hend.b73": {
    "שם": "hend.b73",
    "תפקיד": null,
    "מחלקה": null,
    "רשות": "עיילבון",
    "מייל": "hend.b73@gmail.com",
    "טלפון פרטי": null,
    "טלפון משרד": "048238553"
  },
  "abogeorge1.wk": {
    "שם": "abogeorge1.wk",
    "תפקיד": null,
    "מחלקה": null,
    "רשות": "עיילבון",
    "מייל": "abogeorge1.wk@gmail.com",
    "טלפון פרטי": null,
    "טלפון משרד": "073707901"
  },
  "ranad_1986": {
    "שם": "ranad_1986",
    "תפקיד": null,
    "מחלקה": null,
    "רשות": "עיילבון",
    "מייל": "ranad_1986@hotmail.com",
    "טלפון פרטי": null,
    "טלפון משרד": "046786407"
  },
  "miryamhaib": {
    "שם": "miryamhaib",
    "תפקיד": null,
    "מחלקה": null,
    "רשות": "עיילבון",
    "מייל": "miryamhaib@gmail.com",
    "טלפון פרטי": null,
    "טלפון משרד": null
  },
  "מזכירה מחלקת ספורט": {
    "שם": "מזכירה מחלקת ספורט",
    "תפקיד": null,
    "מחלקה": null,
    "רשות": "עיילבון",
    "מייל": "mha_yuosef@hotmail.com",
    "טלפון פרטי": null,
    "טלפון משרד": "046785680"
  },
  "nabel.emtanes": {
    "שם": "nabel.emtanes",
    "תפקיד": null,
    "מחלקה": null,
    "רשות": "עיילבון",
    "מייל": "nabel.emtanes@gmail.com",
    "טלפון פרטי": null,
    "טלפון משרד": "046789245"
  },
  "נבילה זרייק עביד\tעובדת סוציאלית": {
    "שם": "נבילה זרייק עביד\tעובדת סוציאלית",
    "תפקיד": "עובדת",
    "מחלקה": null,
    "רשות": "עיילבון",
    "מייל": "nabela82@hotmail.com",
    "טלפון פרטי": null,
    "טלפון משרד": "046781750"
  },
  "נואל לואנסי\tעובדת סוציאלית": {
    "שם": "נואל לואנסי\tעובדת סוציאלית",
    "תפקיד": "עובדת",
    "מחלקה": null,
    "רשות": "עיילבון",
    "מייל": "nawal0328@gmail.com",
    "טלפון פרטי": null,
    "טלפון משרד": "046785810"
  },
  "סאהר סמעאן\tמחלקת ספורט": {
    "שם": "סאהר סמעאן\tמחלקת ספורט",
    "תפקיד": null,
    "מחלקה": null,
    "רשות": "עיילבון",
    "מייל": "f_g_saher@hotmail.com",
    "טלפון פרטי": null,
    "טלפון משרד": "046785680"
  },
  "s.soha.hanna78sh": {
    "שם": "s.soha.hanna78sh",
    "תפקיד": null,
    "מחלקה": null,
    "רשות": "עיילבון",
    "מייל": "s.soha.hanna78sh@gmail.com",
    "טלפון פרטי": null,
    "טלפון משרד": "046786407"
  },
  "סלמא סרור\tעובדת זכאות": {
    "שם": "סלמא סרור\tעובדת זכאות",
    "תפקיד": "עובדת",
    "מחלקה": "מחלקת רווחה",
    "רשות": "עיילבון",
    "מייל": "salma_srour@hotmail.com",
    "טלפון פרטי": null,
    "טלפון משרד": "046785810"
  },
  "סמעאן סמעאן\tמחלקת ספורט": {
    "שם": "סמעאן סמעאן\tמחלקת ספורט",
    "תפקיד": "ספורט-מנהל",
    "מחלקה": null,
    "רשות": "עיילבון",
    "מייל": "simaans@hotmail.com",
    "טלפון פרטי": null,
    "טלפון משרד": "046786407"
  },
  "ראפת סמעאן\tאיש אחזקה בי\"ס חט\"ב": {
    "שם": "ראפת סמעאן\tאיש אחזקה בי\"ס חט\"ב",
    "תפקיד": null,
    "מחלקה": null,
    "רשות": "עיילבון",
    "מייל": "rafatsimaan@gmail.com",
    "טלפון פרטי": null,
    "טלפון משרד": "048238553"
  },
  "רזק רושרוש\tמנהל יחידת נוער": {
    "שם": "רזק רושרוש\tמנהל יחידת נוער",
    "תפקיד": "מנהל",
    "מחלקה": "מחלקת נוער",
    "רשות": "עיילבון",
    "מייל": "rezek.rosh@hotmail.com",
    "טלפון פרטי": null,
    "טלפון משרד": "046267074"
  },
  "omar.nsa": {
    "שם": "omar.nsa",
    "תפקיד": null,
    "מחלקה": null,
    "רשות": "עיילבון",
    "מייל": "omar.nsa@eilaboun.muni.il",
    "טלפון פרטי": null,
    "טלפון משרד": null
  }
}